[
  {
    "id": 1,
    "image": "/images/blog_image/blog_occupational.jpg",
    "title": "The Importance of Occupational Standards in Developing Core Learning & Business Skills",
    "date": "January 31st 2025",
    "author": "Jonathan Ford",
    "excerpt": "Using the occupational standards designed to the Regulated Qualifications Framework, LAMS courses ensure that learners study modern, employable skills.",
    "category": "Education"
  },
  {
    "id": 2,
    "image": "/images/blog_image/blog_study.jpg",
    "title": "5 Most Common Master's Degrees in 2025",
    "date": "January 27th 2025",
    "author": "Jonathan Ford",
    "excerpt": "Are you still pondering on what you should study? These programmes have proven to contribute to long-term career growth.",
    "category": "Careers"
  },
  {
    "id": 3,
    "image": "/images/blog_image/blog_learning.jpg",
    "title": "The Critical Power of Self-Assessment for Lifelong Learners",
    "date": "January 24th 2025",
    "author": "Jonathan Ford",
    "excerpt": "Self-assessment is a valuable tool for personal growth and lifelong learning.",
    "category": "Development"
  }
]
